meshconsole/__init__.py
meshconsole/__main__.py
meshconsole/core.py
meshconsole/templates/index.html
meshconsole-2.2.2.dist-info/METADATA
meshconsole-2.2.2.dist-info/WHEEL
meshconsole-2.2.2.dist-info/entry_points.txt
meshconsole-2.2.2.dist-info/licenses/LICENSE
meshconsole-2.2.2.dist-info/RECORD
