Metadata-Version: 2.4
Name: meshconsole
Version: 2.2.2
Summary: A powerful CLI and web interface for Meshtastic mesh networking devices
Project-URL: Homepage, https://github.com/m9wav/MeshConsole
Project-URL: Repository, https://github.com/m9wav/MeshConsole
Project-URL: Issues, https://github.com/m9wav/MeshConsole/issues
Author-email: M9WAV <m9wav@hackers.uk>
License-Expression: MIT
License-File: LICENSE
Keywords: amateur-radio,ham,lora,mesh,meshtastic,networking,radio
Classifier: Development Status :: 4 - Beta
Classifier: Environment :: Console
Classifier: Environment :: Web Environment
Classifier: Intended Audience :: Developers
Classifier: Intended Audience :: End Users/Desktop
Classifier: License :: OSI Approved :: MIT License
Classifier: Operating System :: OS Independent
Classifier: Programming Language :: Python :: 3
Classifier: Programming Language :: Python :: 3.9
Classifier: Programming Language :: Python :: 3.10
Classifier: Programming Language :: Python :: 3.11
Classifier: Programming Language :: Python :: 3.12
Classifier: Topic :: Communications
Classifier: Topic :: Communications :: Ham Radio
Requires-Python: >=3.9
Requires-Dist: flask-cors>=4.0.0
Requires-Dist: flask>=2.0.0
Requires-Dist: meshtastic>=2.0.0
Requires-Dist: protobuf>=3.20.0
Requires-Dist: pypubsub>=4.0.0
Requires-Dist: requests>=2.25.0
Provides-Extra: dev
Requires-Dist: build; extra == 'dev'
Requires-Dist: pytest>=7.0.0; extra == 'dev'
Requires-Dist: twine; extra == 'dev'
